pyotp/__init__.py
pyotp/compat.py
pyotp/hotp.py
pyotp/otp.py
pyotp/py.typed
pyotp/totp.py
pyotp/utils.py
pyotp-2.5.1.dist-info/LICENSE
pyotp-2.5.1.dist-info/METADATA
pyotp-2.5.1.dist-info/WHEEL
pyotp-2.5.1.dist-info/top_level.txt
pyotp-2.5.1.dist-info/RECORD
