Metadata-Version: 2.1
Name: pyotp
Version: 2.5.1
Summary: Python One Time Password Library
Home-page: https://github.com/pyotp/pyotp
Author: PyOTP contributors
Author-email: kislyuk@gmail.com
License: MIT License
Platform: MacOS X
Platform: Posix
Classifier: Intended Audience :: Developers
Classifier: License :: OSI Approved :: MIT License
Classifier: Operating System :: MacOS :: MacOS X
Classifier: Operating System :: POSIX
Classifier: Programming Language :: Python
Classifier: Programming Language :: Python :: 3.4
Classifier: Programming Language :: Python :: 3.5
Classifier: Programming Language :: Python :: 3.6
Classifier: Programming Language :: Python :: 3.7
Classifier: Topic :: Software Development :: Libraries :: Python Modules
